{"errors":[],"warnings":[],"namedChunkGroups":{"polyfill":{"chunks":[5,26],"assets":["webpack-runtime-2ffe90247aecc9eb2330.js","webpack-runtime-2ffe90247aecc9eb2330.js.map","polyfill-5d37448a792f262b0b98.js","polyfill-5d37448a792f262b0b98.js.map"],"children":{},"childAssets":{}},"app":{"chunks":[5,0,25,6],"assets":["webpack-runtime-2ffe90247aecc9eb2330.js","webpack-runtime-2ffe90247aecc9eb2330.js.map","styles.4f3b4bd1b0248128aee5.css","styles-89fd2ae28bdf06750a71.js","styles-89fd2ae28bdf06750a71.js.map","framework-0b9f310da0f8f4ab23be.js","framework-0b9f310da0f8f4ab23be.js.map","app-35ad41725061aa42241c.js","app-35ad41725061aa42241c.js.map"],"children":{},"childAssets":{}},"component---src-pages-api-index-md":{"chunks":[0,1,3,2,4,7],"assets":["styles.4f3b4bd1b0248128aee5.css","styles-89fd2ae28bdf06750a71.js","styles-89fd2ae28bdf06750a71.js.map","0abf01d3-e4ed7e971f4b0e53298f.js","0abf01d3-e4ed7e971f4b0e53298f.js.map","9f96d65d-d7d98a717096a0e50dd4.js","9f96d65d-d7d98a717096a0e50dd4.js.map","8313d723-a9646ab1345d704285a4.js","8313d723-a9646ab1345d704285a4.js.map","commons-947cdfbb50410c661167.js","commons-947cdfbb50410c661167.js.map","component---src-pages-api-index-md-db3c4389a370a129e149.js","component---src-pages-api-index-md-db3c4389a370a129e149.js.map"],"children":{},"childAssets":{}},"component---src-pages-guides-calculated-metrics-api-index-md":{"chunks":[0,1,3,2,4,8],"assets":["styles.4f3b4bd1b0248128aee5.css","styles-89fd2ae28bdf06750a71.js","styles-89fd2ae28bdf06750a71.js.map","0abf01d3-e4ed7e971f4b0e53298f.js","0abf01d3-e4ed7e971f4b0e53298f.js.map","9f96d65d-d7d98a717096a0e50dd4.js","9f96d65d-d7d98a717096a0e50dd4.js.map","8313d723-a9646ab1345d704285a4.js","8313d723-a9646ab1345d704285a4.js.map","commons-947cdfbb50410c661167.js","commons-947cdfbb50410c661167.js.map","component---src-pages-guides-calculated-metrics-api-index-md-42b6e84134fda6378682.js","component---src-pages-guides-calculated-metrics-api-index-md-42b6e84134fda6378682.js.map"],"children":{},"childAssets":{}},"component---src-pages-guides-creating-oauth-client-index-md":{"chunks":[0,1,3,2,4,9],"assets":["styles.4f3b4bd1b0248128aee5.css","styles-89fd2ae28bdf06750a71.js","styles-89fd2ae28bdf06750a71.js.map","0abf01d3-e4ed7e971f4b0e53298f.js","0abf01d3-e4ed7e971f4b0e53298f.js.map","9f96d65d-d7d98a717096a0e50dd4.js","9f96d65d-d7d98a717096a0e50dd4.js.map","8313d723-a9646ab1345d704285a4.js","8313d723-a9646ab1345d704285a4.js.map","commons-947cdfbb50410c661167.js","commons-947cdfbb50410c661167.js.map","component---src-pages-guides-creating-oauth-client-index-md-80e71159532f007dabe0.js","component---src-pages-guides-creating-oauth-client-index-md-80e71159532f007dabe0.js.map"],"children":{},"childAssets":{}},"component---src-pages-guides-discovery-api-index-md":{"chunks":[0,1,3,2,4,10],"assets":["styles.4f3b4bd1b0248128aee5.css","styles-89fd2ae28bdf06750a71.js","styles-89fd2ae28bdf06750a71.js.map","0abf01d3-e4ed7e971f4b0e53298f.js","0abf01d3-e4ed7e971f4b0e53298f.js.map","9f96d65d-d7d98a717096a0e50dd4.js","9f96d65d-d7d98a717096a0e50dd4.js.map","8313d723-a9646ab1345d704285a4.js","8313d723-a9646ab1345d704285a4.js.map","commons-947cdfbb50410c661167.js","commons-947cdfbb50410c661167.js.map","component---src-pages-guides-discovery-api-index-md-ee40cc745a203ad81162.js","component---src-pages-guides-discovery-api-index-md-ee40cc745a203ad81162.js.map"],"children":{},"childAssets":{}},"component---src-pages-guides-index-md":{"chunks":[0,1,3,2,4,11],"assets":["styles.4f3b4bd1b0248128aee5.css","styles-89fd2ae28bdf06750a71.js","styles-89fd2ae28bdf06750a71.js.map","0abf01d3-e4ed7e971f4b0e53298f.js","0abf01d3-e4ed7e971f4b0e53298f.js.map","9f96d65d-d7d98a717096a0e50dd4.js","9f96d65d-d7d98a717096a0e50dd4.js.map","8313d723-a9646ab1345d704285a4.js","8313d723-a9646ab1345d704285a4.js.map","commons-947cdfbb50410c661167.js","commons-947cdfbb50410c661167.js.map","component---src-pages-guides-index-md-bbe7b07ed917f3f19f26.js","component---src-pages-guides-index-md-bbe7b07ed917f3f19f26.js.map"],"children":{},"childAssets":{}},"component---src-pages-guides-jwt-authentication-index-md":{"chunks":[0,1,3,2,4,12],"assets":["styles.4f3b4bd1b0248128aee5.css","styles-89fd2ae28bdf06750a71.js","styles-89fd2ae28bdf06750a71.js.map","0abf01d3-e4ed7e971f4b0e53298f.js","0abf01d3-e4ed7e971f4b0e53298f.js.map","9f96d65d-d7d98a717096a0e50dd4.js","9f96d65d-d7d98a717096a0e50dd4.js.map","8313d723-a9646ab1345d704285a4.js","8313d723-a9646ab1345d704285a4.js.map","commons-947cdfbb50410c661167.js","commons-947cdfbb50410c661167.js.map","component---src-pages-guides-jwt-authentication-index-md-119dc4ca40f426df8e79.js","component---src-pages-guides-jwt-authentication-index-md-119dc4ca40f426df8e79.js.map"],"children":{},"childAssets":{}},"component---src-pages-guides-migrating-index-md":{"chunks":[0,1,3,2,4,13],"assets":["styles.4f3b4bd1b0248128aee5.css","styles-89fd2ae28bdf06750a71.js","styles-89fd2ae28bdf06750a71.js.map","0abf01d3-e4ed7e971f4b0e53298f.js","0abf01d3-e4ed7e971f4b0e53298f.js.map","9f96d65d-d7d98a717096a0e50dd4.js","9f96d65d-d7d98a717096a0e50dd4.js.map","8313d723-a9646ab1345d704285a4.js","8313d723-a9646ab1345d704285a4.js.map","commons-947cdfbb50410c661167.js","commons-947cdfbb50410c661167.js.map","component---src-pages-guides-migrating-index-md-944976e3d338cb8d2a7f.js","component---src-pages-guides-migrating-index-md-944976e3d338cb8d2a7f.js.map"],"children":{},"childAssets":{}},"component---src-pages-guides-oauth-using-curl-index-md":{"chunks":[0,1,3,2,4,14],"assets":["styles.4f3b4bd1b0248128aee5.css","styles-89fd2ae28bdf06750a71.js","styles-89fd2ae28bdf06750a71.js.map","0abf01d3-e4ed7e971f4b0e53298f.js","0abf01d3-e4ed7e971f4b0e53298f.js.map","9f96d65d-d7d98a717096a0e50dd4.js","9f96d65d-d7d98a717096a0e50dd4.js.map","8313d723-a9646ab1345d704285a4.js","8313d723-a9646ab1345d704285a4.js.map","commons-947cdfbb50410c661167.js","commons-947cdfbb50410c661167.js.map","component---src-pages-guides-oauth-using-curl-index-md-8415dd2e728fc0ad99c0.js","component---src-pages-guides-oauth-using-curl-index-md-8415dd2e728fc0ad99c0.js.map"],"children":{},"childAssets":{}},"component---src-pages-guides-oauth-using-postman-index-md":{"chunks":[0,1,3,2,4,15],"assets":["styles.4f3b4bd1b0248128aee5.css","styles-89fd2ae28bdf06750a71.js","styles-89fd2ae28bdf06750a71.js.map","0abf01d3-e4ed7e971f4b0e53298f.js","0abf01d3-e4ed7e971f4b0e53298f.js.map","9f96d65d-d7d98a717096a0e50dd4.js","9f96d65d-d7d98a717096a0e50dd4.js.map","8313d723-a9646ab1345d704285a4.js","8313d723-a9646ab1345d704285a4.js.map","commons-947cdfbb50410c661167.js","commons-947cdfbb50410c661167.js.map","component---src-pages-guides-oauth-using-postman-index-md-fb0c53a1f65032bda86d.js","component---src-pages-guides-oauth-using-postman-index-md-fb0c53a1f65032bda86d.js.map"],"children":{},"childAssets":{}},"component---src-pages-guides-reporting-api-index-md":{"chunks":[0,1,3,2,4,16],"assets":["styles.4f3b4bd1b0248128aee5.css","styles-89fd2ae28bdf06750a71.js","styles-89fd2ae28bdf06750a71.js.map","0abf01d3-e4ed7e971f4b0e53298f.js","0abf01d3-e4ed7e971f4b0e53298f.js.map","9f96d65d-d7d98a717096a0e50dd4.js","9f96d65d-d7d98a717096a0e50dd4.js.map","8313d723-a9646ab1345d704285a4.js","8313d723-a9646ab1345d704285a4.js.map","commons-947cdfbb50410c661167.js","commons-947cdfbb50410c661167.js.map","component---src-pages-guides-reporting-api-index-md-6e5f749f4b5832653211.js","component---src-pages-guides-reporting-api-index-md-6e5f749f4b5832653211.js.map"],"children":{},"childAssets":{}},"component---src-pages-guides-reporting-api-reporting-breakdowns-index-md":{"chunks":[0,1,3,2,4,17],"assets":["styles.4f3b4bd1b0248128aee5.css","styles-89fd2ae28bdf06750a71.js","styles-89fd2ae28bdf06750a71.js.map","0abf01d3-e4ed7e971f4b0e53298f.js","0abf01d3-e4ed7e971f4b0e53298f.js.map","9f96d65d-d7d98a717096a0e50dd4.js","9f96d65d-d7d98a717096a0e50dd4.js.map","8313d723-a9646ab1345d704285a4.js","8313d723-a9646ab1345d704285a4.js.map","commons-947cdfbb50410c661167.js","commons-947cdfbb50410c661167.js.map","component---src-pages-guides-reporting-api-reporting-breakdowns-index-md-5f27a25805b295978a63.js","component---src-pages-guides-reporting-api-reporting-breakdowns-index-md-5f27a25805b295978a63.js.map"],"children":{},"childAssets":{}},"component---src-pages-guides-reporting-api-reporting-breakdowns-reporting-multiple-breakdowns-index-md":{"chunks":[0,1,3,2,4,18],"assets":["styles.4f3b4bd1b0248128aee5.css","styles-89fd2ae28bdf06750a71.js","styles-89fd2ae28bdf06750a71.js.map","0abf01d3-e4ed7e971f4b0e53298f.js","0abf01d3-e4ed7e971f4b0e53298f.js.map","9f96d65d-d7d98a717096a0e50dd4.js","9f96d65d-d7d98a717096a0e50dd4.js.map","8313d723-a9646ab1345d704285a4.js","8313d723-a9646ab1345d704285a4.js.map","commons-947cdfbb50410c661167.js","commons-947cdfbb50410c661167.js.map","component---src-pages-guides-reporting-api-reporting-breakdowns-reporting-multiple-breakdowns-index-md-e3e8b2a155725fc979c8.js","component---src-pages-guides-reporting-api-reporting-breakdowns-reporting-multiple-breakdowns-index-md-e3e8b2a155725fc979c8.js.map"],"children":{},"childAssets":{}},"component---src-pages-guides-reporting-api-reporting-tips-tricks-index-md":{"chunks":[0,1,3,2,4,19],"assets":["styles.4f3b4bd1b0248128aee5.css","styles-89fd2ae28bdf06750a71.js","styles-89fd2ae28bdf06750a71.js.map","0abf01d3-e4ed7e971f4b0e53298f.js","0abf01d3-e4ed7e971f4b0e53298f.js.map","9f96d65d-d7d98a717096a0e50dd4.js","9f96d65d-d7d98a717096a0e50dd4.js.map","8313d723-a9646ab1345d704285a4.js","8313d723-a9646ab1345d704285a4.js.map","commons-947cdfbb50410c661167.js","commons-947cdfbb50410c661167.js.map","component---src-pages-guides-reporting-api-reporting-tips-tricks-index-md-55d140d13b3ca0cf8292.js","component---src-pages-guides-reporting-api-reporting-tips-tricks-index-md-55d140d13b3ca0cf8292.js.map"],"children":{},"childAssets":{}},"component---src-pages-guides-segments-api-index-md":{"chunks":[0,1,3,2,4,20],"assets":["styles.4f3b4bd1b0248128aee5.css","styles-89fd2ae28bdf06750a71.js","styles-89fd2ae28bdf06750a71.js.map","0abf01d3-e4ed7e971f4b0e53298f.js","0abf01d3-e4ed7e971f4b0e53298f.js.map","9f96d65d-d7d98a717096a0e50dd4.js","9f96d65d-d7d98a717096a0e50dd4.js.map","8313d723-a9646ab1345d704285a4.js","8313d723-a9646ab1345d704285a4.js.map","commons-947cdfbb50410c661167.js","commons-947cdfbb50410c661167.js.map","component---src-pages-guides-segments-api-index-md-434db90355f8d37c02ec.js","component---src-pages-guides-segments-api-index-md-434db90355f8d37c02ec.js.map"],"children":{},"childAssets":{}},"component---src-pages-index-md":{"chunks":[0,1,3,2,4,21],"assets":["styles.4f3b4bd1b0248128aee5.css","styles-89fd2ae28bdf06750a71.js","styles-89fd2ae28bdf06750a71.js.map","0abf01d3-e4ed7e971f4b0e53298f.js","0abf01d3-e4ed7e971f4b0e53298f.js.map","9f96d65d-d7d98a717096a0e50dd4.js","9f96d65d-d7d98a717096a0e50dd4.js.map","8313d723-a9646ab1345d704285a4.js","8313d723-a9646ab1345d704285a4.js.map","commons-947cdfbb50410c661167.js","commons-947cdfbb50410c661167.js.map","component---src-pages-index-md-8723d55e825ffee7adf3.js","component---src-pages-index-md-8723d55e825ffee7adf3.js.map"],"children":{},"childAssets":{}},"component---src-pages-support-contribute-index-md":{"chunks":[0,1,3,2,4,22],"assets":["styles.4f3b4bd1b0248128aee5.css","styles-89fd2ae28bdf06750a71.js","styles-89fd2ae28bdf06750a71.js.map","0abf01d3-e4ed7e971f4b0e53298f.js","0abf01d3-e4ed7e971f4b0e53298f.js.map","9f96d65d-d7d98a717096a0e50dd4.js","9f96d65d-d7d98a717096a0e50dd4.js.map","8313d723-a9646ab1345d704285a4.js","8313d723-a9646ab1345d704285a4.js.map","commons-947cdfbb50410c661167.js","commons-947cdfbb50410c661167.js.map","component---src-pages-support-contribute-index-md-165e991d425bcdc5d8b3.js","component---src-pages-support-contribute-index-md-165e991d425bcdc5d8b3.js.map"],"children":{},"childAssets":{}},"component---src-pages-support-faq-index-md":{"chunks":[0,1,3,2,4,23],"assets":["styles.4f3b4bd1b0248128aee5.css","styles-89fd2ae28bdf06750a71.js","styles-89fd2ae28bdf06750a71.js.map","0abf01d3-e4ed7e971f4b0e53298f.js","0abf01d3-e4ed7e971f4b0e53298f.js.map","9f96d65d-d7d98a717096a0e50dd4.js","9f96d65d-d7d98a717096a0e50dd4.js.map","8313d723-a9646ab1345d704285a4.js","8313d723-a9646ab1345d704285a4.js.map","commons-947cdfbb50410c661167.js","commons-947cdfbb50410c661167.js.map","component---src-pages-support-faq-index-md-8ae93c707dd803a8d814.js","component---src-pages-support-faq-index-md-8ae93c707dd803a8d814.js.map"],"children":{},"childAssets":{}},"component---src-pages-support-index-md":{"chunks":[0,1,3,2,4,24],"assets":["styles.4f3b4bd1b0248128aee5.css","styles-89fd2ae28bdf06750a71.js","styles-89fd2ae28bdf06750a71.js.map","0abf01d3-e4ed7e971f4b0e53298f.js","0abf01d3-e4ed7e971f4b0e53298f.js.map","9f96d65d-d7d98a717096a0e50dd4.js","9f96d65d-d7d98a717096a0e50dd4.js.map","8313d723-a9646ab1345d704285a4.js","8313d723-a9646ab1345d704285a4.js.map","commons-947cdfbb50410c661167.js","commons-947cdfbb50410c661167.js.map","component---src-pages-support-index-md-8856c9fbc0ca6f915094.js","component---src-pages-support-index-md-8856c9fbc0ca6f915094.js.map"],"children":{},"childAssets":{}}},"assetsByChunkName":{"polyfill":["webpack-runtime-2ffe90247aecc9eb2330.js","polyfill-5d37448a792f262b0b98.js"],"app":["webpack-runtime-2ffe90247aecc9eb2330.js","styles.4f3b4bd1b0248128aee5.css","styles-89fd2ae28bdf06750a71.js","framework-0b9f310da0f8f4ab23be.js","app-35ad41725061aa42241c.js"],"component---src-pages-api-index-md":["styles.4f3b4bd1b0248128aee5.css","styles-89fd2ae28bdf06750a71.js","0abf01d3-e4ed7e971f4b0e53298f.js","9f96d65d-d7d98a717096a0e50dd4.js","8313d723-a9646ab1345d704285a4.js","commons-947cdfbb50410c661167.js","component---src-pages-api-index-md-db3c4389a370a129e149.js"],"component---src-pages-guides-calculated-metrics-api-index-md":["styles.4f3b4bd1b0248128aee5.css","styles-89fd2ae28bdf06750a71.js","0abf01d3-e4ed7e971f4b0e53298f.js","9f96d65d-d7d98a717096a0e50dd4.js","8313d723-a9646ab1345d704285a4.js","commons-947cdfbb50410c661167.js","component---src-pages-guides-calculated-metrics-api-index-md-42b6e84134fda6378682.js"],"component---src-pages-guides-creating-oauth-client-index-md":["styles.4f3b4bd1b0248128aee5.css","styles-89fd2ae28bdf06750a71.js","0abf01d3-e4ed7e971f4b0e53298f.js","9f96d65d-d7d98a717096a0e50dd4.js","8313d723-a9646ab1345d704285a4.js","commons-947cdfbb50410c661167.js","component---src-pages-guides-creating-oauth-client-index-md-80e71159532f007dabe0.js"],"component---src-pages-guides-discovery-api-index-md":["styles.4f3b4bd1b0248128aee5.css","styles-89fd2ae28bdf06750a71.js","0abf01d3-e4ed7e971f4b0e53298f.js","9f96d65d-d7d98a717096a0e50dd4.js","8313d723-a9646ab1345d704285a4.js","commons-947cdfbb50410c661167.js","component---src-pages-guides-discovery-api-index-md-ee40cc745a203ad81162.js"],"component---src-pages-guides-index-md":["styles.4f3b4bd1b0248128aee5.css","styles-89fd2ae28bdf06750a71.js","0abf01d3-e4ed7e971f4b0e53298f.js","9f96d65d-d7d98a717096a0e50dd4.js","8313d723-a9646ab1345d704285a4.js","commons-947cdfbb50410c661167.js","component---src-pages-guides-index-md-bbe7b07ed917f3f19f26.js"],"component---src-pages-guides-jwt-authentication-index-md":["styles.4f3b4bd1b0248128aee5.css","styles-89fd2ae28bdf06750a71.js","0abf01d3-e4ed7e971f4b0e53298f.js","9f96d65d-d7d98a717096a0e50dd4.js","8313d723-a9646ab1345d704285a4.js","commons-947cdfbb50410c661167.js","component---src-pages-guides-jwt-authentication-index-md-119dc4ca40f426df8e79.js"],"component---src-pages-guides-migrating-index-md":["styles.4f3b4bd1b0248128aee5.css","styles-89fd2ae28bdf06750a71.js","0abf01d3-e4ed7e971f4b0e53298f.js","9f96d65d-d7d98a717096a0e50dd4.js","8313d723-a9646ab1345d704285a4.js","commons-947cdfbb50410c661167.js","component---src-pages-guides-migrating-index-md-944976e3d338cb8d2a7f.js"],"component---src-pages-guides-oauth-using-curl-index-md":["styles.4f3b4bd1b0248128aee5.css","styles-89fd2ae28bdf06750a71.js","0abf01d3-e4ed7e971f4b0e53298f.js","9f96d65d-d7d98a717096a0e50dd4.js","8313d723-a9646ab1345d704285a4.js","commons-947cdfbb50410c661167.js","component---src-pages-guides-oauth-using-curl-index-md-8415dd2e728fc0ad99c0.js"],"component---src-pages-guides-oauth-using-postman-index-md":["styles.4f3b4bd1b0248128aee5.css","styles-89fd2ae28bdf06750a71.js","0abf01d3-e4ed7e971f4b0e53298f.js","9f96d65d-d7d98a717096a0e50dd4.js","8313d723-a9646ab1345d704285a4.js","commons-947cdfbb50410c661167.js","component---src-pages-guides-oauth-using-postman-index-md-fb0c53a1f65032bda86d.js"],"component---src-pages-guides-reporting-api-index-md":["styles.4f3b4bd1b0248128aee5.css","styles-89fd2ae28bdf06750a71.js","0abf01d3-e4ed7e971f4b0e53298f.js","9f96d65d-d7d98a717096a0e50dd4.js","8313d723-a9646ab1345d704285a4.js","commons-947cdfbb50410c661167.js","component---src-pages-guides-reporting-api-index-md-6e5f749f4b5832653211.js"],"component---src-pages-guides-reporting-api-reporting-breakdowns-index-md":["styles.4f3b4bd1b0248128aee5.css","styles-89fd2ae28bdf06750a71.js","0abf01d3-e4ed7e971f4b0e53298f.js","9f96d65d-d7d98a717096a0e50dd4.js","8313d723-a9646ab1345d704285a4.js","commons-947cdfbb50410c661167.js","component---src-pages-guides-reporting-api-reporting-breakdowns-index-md-5f27a25805b295978a63.js"],"component---src-pages-guides-reporting-api-reporting-breakdowns-reporting-multiple-breakdowns-index-md":["styles.4f3b4bd1b0248128aee5.css","styles-89fd2ae28bdf06750a71.js","0abf01d3-e4ed7e971f4b0e53298f.js","9f96d65d-d7d98a717096a0e50dd4.js","8313d723-a9646ab1345d704285a4.js","commons-947cdfbb50410c661167.js","component---src-pages-guides-reporting-api-reporting-breakdowns-reporting-multiple-breakdowns-index-md-e3e8b2a155725fc979c8.js"],"component---src-pages-guides-reporting-api-reporting-tips-tricks-index-md":["styles.4f3b4bd1b0248128aee5.css","styles-89fd2ae28bdf06750a71.js","0abf01d3-e4ed7e971f4b0e53298f.js","9f96d65d-d7d98a717096a0e50dd4.js","8313d723-a9646ab1345d704285a4.js","commons-947cdfbb50410c661167.js","component---src-pages-guides-reporting-api-reporting-tips-tricks-index-md-55d140d13b3ca0cf8292.js"],"component---src-pages-guides-segments-api-index-md":["styles.4f3b4bd1b0248128aee5.css","styles-89fd2ae28bdf06750a71.js","0abf01d3-e4ed7e971f4b0e53298f.js","9f96d65d-d7d98a717096a0e50dd4.js","8313d723-a9646ab1345d704285a4.js","commons-947cdfbb50410c661167.js","component---src-pages-guides-segments-api-index-md-434db90355f8d37c02ec.js"],"component---src-pages-index-md":["styles.4f3b4bd1b0248128aee5.css","styles-89fd2ae28bdf06750a71.js","0abf01d3-e4ed7e971f4b0e53298f.js","9f96d65d-d7d98a717096a0e50dd4.js","8313d723-a9646ab1345d704285a4.js","commons-947cdfbb50410c661167.js","component---src-pages-index-md-8723d55e825ffee7adf3.js"],"component---src-pages-support-contribute-index-md":["styles.4f3b4bd1b0248128aee5.css","styles-89fd2ae28bdf06750a71.js","0abf01d3-e4ed7e971f4b0e53298f.js","9f96d65d-d7d98a717096a0e50dd4.js","8313d723-a9646ab1345d704285a4.js","commons-947cdfbb50410c661167.js","component---src-pages-support-contribute-index-md-165e991d425bcdc5d8b3.js"],"component---src-pages-support-faq-index-md":["styles.4f3b4bd1b0248128aee5.css","styles-89fd2ae28bdf06750a71.js","0abf01d3-e4ed7e971f4b0e53298f.js","9f96d65d-d7d98a717096a0e50dd4.js","8313d723-a9646ab1345d704285a4.js","commons-947cdfbb50410c661167.js","component---src-pages-support-faq-index-md-8ae93c707dd803a8d814.js"],"component---src-pages-support-index-md":["styles.4f3b4bd1b0248128aee5.css","styles-89fd2ae28bdf06750a71.js","0abf01d3-e4ed7e971f4b0e53298f.js","9f96d65d-d7d98a717096a0e50dd4.js","8313d723-a9646ab1345d704285a4.js","commons-947cdfbb50410c661167.js","component---src-pages-support-index-md-8856c9fbc0ca6f915094.js"]}}